{
  "name": "Murkrow",
  "nationalPokedexNumber": 198,
  "secondaryType": "flying",
  "behaviour": {
    "moving": {
      "fly": {
        "canFly": true
      },
      "walk": {
        "walkSpeed": 0.28
      }
    },
    "resting": {
      "canSleep": true,
      "times": "day"
    }
  },
  "catchRate": 30,
  "shoulderMountable": false,
  "baseExperienceYield": 81,
  "experienceGroup": "medium_slow",
  "baseScale": 0.8,
  "hitbox": {
    "width": 0.65,
    "height": 1,
    "fixed": false
  },
  "baseFriendship": 35,
  "evYield": {
    "hp": 0,
    "attack": 0,
    "defence": 0,
    "special_attack": 0,
    "special_defence": 0,
    "speed": 1
  },
  "height": 5,
  "weight": 21,
  "aspects": []
}