{
  "name": "Barbaracle",
  "nationalPokedexNumber": 689,
  "secondaryType": "water",
  "catchRate": 45,
  "shoulderMountable": false,
  "baseExperienceYield": 175,
  "experienceGroup": "medium_fast",
  "preEvolution": "binacle",
  "baseScale": 1,
  "hitbox": {
    "width": 1,
    "height": 1,
    "fixed": false
  },
  "baseFriendship": 50,
  "evYield": {
    "hp": 0,
    "attack": 2,
    "defence": 0,
    "special_attack": 0,
    "special_defence": 0,
    "speed": 0
  },
  "height": 13,
  "weight": 960,
  "aspects": []
}