{
  "name": "Quaxwell",
  "nationalPokedexNumber": 913,
  "catchRate": 45,
  "baseExperienceYield": 144,
  "baseFriendship": 50,
  "evYield": {
    "hp": 0,
    "attack": 2,
    "defence": 0,
    "special_attack": 0,
    "special_defence": 0,
    "speed": 0
  },
  "experienceGroup": "medium_slow",
  "behaviour": {
    "moving": {
      "walk": {
        "walkSpeed": 0.3
      }
    },
    "resting": {
      "canSleep": true,
      "willSleepOnBed": false,
      "depth": "normal",
      "light": "0-4"
    }
  },
  "aspects": [],
  "height": 12,
  "weight": 215,
  "preEvolution": "quaxly",
  "baseScale": 0.6,
  "hitbox": {
    "width": 0.8,
    "height": 2,
    "fixed": false
  }
}