{
  "name": "Pidove",
  "nationalPokedexNumber": 519,
  "secondaryType": "flying",
  "catchRate": 255,
  "shoulderMountable": false,
  "baseExperienceYield": 53,
  "experienceGroup": "medium_slow",
  "behaviour": {
    "moving": {
      "fly": {
        "canFly": true
      }
    }
  },
  "baseScale": 0.7,
  "hitbox": {
    "width": 0.5,
    "height": 0.8,
    "fixed": false
  },
  "baseFriendship": 50,
  "evYield": {
    "hp": 0,
    "attack": 1,
    "defence": 0,
    "special_attack": 0,
    "special_defence": 0,
    "speed": 0
  },
  "height": 3,
  "weight": 21,
  "aspects": []
}